libdc3/__init__.py
libdc3/_version.py
libdc3/config.py
libdc3/labels.py
libdc3/units.py
libdc3/utils.py
libdc3/assets/__init__.py
libdc3/assets/cms_logo.png
libdc3/methods/__init__.py
libdc3/methods/acc_lumi_analyzer.py
libdc3/methods/bril_actions.py
libdc3/methods/era_plotter.py
libdc3/methods/json_producer.py
libdc3/methods/lumiloss_analyzer.py
libdc3/methods/lumiloss_plotter.py
libdc3/methods/next_call.py
libdc3/methods/rr_actions.py
libdc3/methods/t0_actions.py
libdc3/services/__init__.py
libdc3/services/bril/__init__.py
libdc3/services/bril/client.py
libdc3/services/bril/exceptions.py
libdc3/services/caf/__init__.py
libdc3/services/caf/client.py
libdc3/services/dqmgui/__init__.py
libdc3/services/dqmgui/client.py
libdc3/services/t0/__init__.py
libdc3/services/t0/client.py
libdc3-1.3.2.dist-info/licenses/LICENSE
libdc3-1.3.2.dist-info/METADATA
libdc3-1.3.2.dist-info/WHEEL
libdc3-1.3.2.dist-info/top_level.txt
libdc3-1.3.2.dist-info/RECORD
