Metadata-Version: 2.4
Name: libdc3
Version: 1.3.2
Summary: The python library for dc3 and central DC shifters
Author-email: Gabriel Moreira <gabriel.moreira@cern.ch>
Project-URL: Repository, https://gitlab.cern.ch/cms-dqmdc/libraries/python-libdc3
Classifier: Development Status :: 5 - Production/Stable
Classifier: Programming Language :: Python :: 3.9
Classifier: Programming Language :: Python :: 3.10
Classifier: Programming Language :: Python :: 3.11
Classifier: Programming Language :: Python :: 3.12
Requires-Python: >=3.9
License-File: LICENSE
Requires-Dist: requests<3.0.0,>=2.31.0
Requires-Dist: paramiko<4.0.0,>=3.4.1
Requires-Dist: beautifulsoup4<5.0.0,>=4.12.3
Requires-Dist: runregistry<4.0.0,>=3.1.1
Requires-Dist: matplotlib<4.0.0,>=3.9.2
Requires-Dist: numpy>=1.22.0
Dynamic: license-file
